fastga/__init__.py
fastga/operators.py
fastga/sampling.py
fastga/utils.py
fastga-1.0.0.dist-info/DESCRIPTION.rst
fastga-1.0.0.dist-info/METADATA
fastga-1.0.0.dist-info/RECORD
fastga-1.0.0.dist-info/WHEEL
fastga-1.0.0.dist-info/metadata.json
fastga-1.0.0.dist-info/top_level.txt
