Metadata-Version: 2.0
Name: fastga
Version: 1.0.0
Summary: Implementation of the so-called Heavy-Tailed Mutation Operator
Home-page: https://github.com/FastGA/fast-genetic-algorithms
Author: The FastGA team
Author-email: UNKNOWN
License: Unlicense
Platform: UNKNOWN
Classifier: Programming Language :: Python
Classifier: Operating System :: OS Independent
Classifier: License :: Public Domain
Classifier: Programming Language :: Python :: 3.5
Classifier: Topic :: Scientific/Engineering :: Artificial Intelligence
Requires-Dist: numpy (>=1.7.0)
